tests/__init__.py
tests/conftest.py
tests/test_zen_han_converter.py
zen_han_converter/__init__.py
zen_han_converter/han_to_zen_table.py
zen_han_converter/zen_han_converter.py
zen_han_converter/zen_to_han_table.py
zen_han_converter-1.1.0.dist-info/METADATA
zen_han_converter-1.1.0.dist-info/WHEEL
zen_han_converter-1.1.0.dist-info/top_level.txt
zen_han_converter-1.1.0.dist-info/RECORD
