Metadata-Version: 2.1
Name: zen_han_converter
Version: 1.1.0
Summary: Converts full-width and half-width characters.
Home-page: https://github.com/n4cl/zen_han_converter.git
Author: n4cl
Author-email: devn4cl@gmail.com
License: MIT
Classifier: Programming Language :: Python :: 3.8
Classifier: Programming Language :: Python :: 3.9
Classifier: Programming Language :: Python :: 3.10
Classifier: Programming Language :: Python :: 3.11
